{
  "table": "nickname",
  "row_count": 211,
  "columns": [
    "id",
    "scenario_id",
    "disp_order",
    "group_id",
    "rank",
    "chara_data_id",
    "user_show",
    "receive_condition_type",
    "start_date",
    "end_date"
  ],
  "rows": [
    {
      "id": 1,
      "scenario_id": 0,
      "disp_order": 15,
      "group_id": 15,
      "rank": 1,
      "chara_data_id": 0,
      "user_show": 1,
      "receive_condition_type": 3,
      "start_date": 1483228800,
      "end_date": 2524608000
    },
    {
      "id": 2,
      "scenario_id": 0,
      "disp_order": 16,
      "group_id": 16,
      "rank": 1,
      "chara_data_id": 0,
      "user_show": 1,
      "receive_condition_type": 3,
      "start_date": 1483228800,
      "end_date": 2524608000
    },
    {
      "id": 3,
      "scenario_id": 0,
      "disp_order": 14,
      "group_id": 14,
      "rank": 1,
      "chara_data_id": 0,
      "user_show": 1,
      "receive_condition_type": 3,
      "start_date": 1483228800,
      "end_date": 2524608000
    },
    {
      "id": 4,
      "scenario_id": 0,
      "disp_order": 22,
      "group_id": 22,
      "rank": 1,
      "chara_data_id": 0,
      "user_show": 1,
      "receive_condition_type": 1,
      "start_date": 1483228800,
      "end_date": 2524608000
    },
    {
      "id": 5,
      "scenario_id": 0,
      "disp_order": 3052,
      "group_id": 3052,
      "rank": 3,
      "chara_data_id": 1052,
      "user_show": 1,
      "receive_condition_type": 3,
      "start_date": 1483228800,
      "end_date": 2524608000
    },
    {
      "id": 6,
      "scenario_id": 0,
      "disp_order": 41,
      "group_id": 41,
      "rank": 1,
      "chara_data_id": 0,
      "user_show": 1,
      "receive_condition_type": 1,
      "start_date": 1763330400,
      "end_date": 2524608000
    },
    {
      "id": 7,
      "scenario_id": 0,
      "disp_order": 42,
      "group_id": 42,
      "rank": 1,
      "chara_data_id": 0,
      "user_show": 1,
      "receive_condition_type": 1,
      "start_date": 1483228800,
      "end_date": 2524608000
    },
    {
      "id": 8,
      "scenario_id": 0,
      "disp_order": 31,
      "group_id": 31,
      "rank": 1,
      "chara_data_id": 0,
      "user_show": 1,
      "receive_condition_type": 3,
      "start_date": 1483228800,
      "end_date": 2524608000
    },
    {
      "id": 9,
      "scenario_id": 0,
      "disp_order": 23,
      "group_id": 23,
      "rank": 1,
      "chara_data_id": 0,
      "user_show": 1,
      "receive_condition_type": 3,
      "start_date": 1483228800,
      "end_date": 2524608000
    },
    {
      "id": 10,
      "scenario_id": 0,
      "disp_order": 2035,
      "group_id": 2035,
      "rank": 2,
      "chara_data_id": 0,
      "user_show": 1,
      "receive_condition_type": 3,
      "start_date": 1483228800,
      "end_date": 2524608000
    },
    {
      "id": 12,
      "scenario_id": 0,
      "disp_order": 4,
      "group_id": 4,
      "rank": 1,
      "chara_data_id": 0,
      "user_show": 1,
      "receive_condition_type": 3,
      "start_date": 1483228800,
      "end_date": 2524608000
    },
    {
      "id": 13,
      "scenario_id": 0,
      "disp_order": 9,
      "group_id": 9,
      "rank": 1,
      "chara_data_id": 0,
      "user_show": 1,
      "receive_condition_type": 3,
      "start_date": 1483228800,
      "end_date": 2524608000
    },
    {
      "id": 14,
      "scenario_id": 0,
      "disp_order": 7,
      "group_id": 7,
      "rank": 1,
      "chara_data_id": 0,
      "user_show": 1,
      "receive_condition_type": 3,
      "start_date": 1483228800,
      "end_date": 2524608000
    },
    {
      "id": 15,
      "scenario_id": 0,
      "disp_order": 8,
      "group_id": 8,
      "rank": 1,
      "chara_data_id": 0,
      "user_show": 1,
      "receive_condition_type": 3,
      "start_date": 1483228800,
      "end_date": 2524608000
    },
    {
      "id": 16,
      "scenario_id": 0,
      "disp_order": 10,
      "group_id": 10,
      "rank": 1,
      "chara_data_id": 0,
      "user_show": 1,
      "receive_condition_type": 3,
      "start_date": 1483228800,
      "end_date": 2524608000
    },
    {
      "id": 17,
      "scenario_id": 0,
      "disp_order": 17,
      "group_id": 17,
      "rank": 1,
      "chara_data_id": 0,
      "user_show": 1,
      "receive_condition_type": 3,
      "start_date": 1483228800,
      "end_date": 2524608000
    },
    {
      "id": 18,
      "scenario_id": 0,
      "disp_order": 29,
      "group_id": 29,
      "rank": 1,
      "chara_data_id": 0,
      "user_show": 1,
      "receive_condition_type": 3,
      "start_date": 1483228800,
      "end_date": 2524608000
    },
    {
      "id": 19,
      "scenario_id": 0,
      "disp_order": 6,
      "group_id": 6,
      "rank": 1,
      "chara_data_id": 0,
      "user_show": 1,
      "receive_condition_type": 3,
      "start_date": 1483228800,
      "end_date": 2524608000
    },
    {
      "id": 20,
      "scenario_id": 0,
      "disp_order": 40,
      "group_id": 40,
      "rank": 1,
      "chara_data_id": 0,
      "user_show": 1,
      "receive_condition_type": 1,
      "start_date": 1483228800,
      "end_date": 2524608000
    },
    {
      "id": 21,
      "scenario_id": 0,
      "disp_order": 33,
      "group_id": 33,
      "rank": 1,
      "chara_data_id": 0,
      "user_show": 1,
      "receive_condition_type": 3,
      "start_date": 1483228800,
      "end_date": 2524608000
    },
    {
      "id": 22,
      "scenario_id": 0,
      "disp_order": 13,
      "group_id": 13,
      "rank": 1,
      "chara_data_id": 0,
      "user_show": 1,
      "receive_condition_type": 3,
      "start_date": 1483228800,
      "end_date": 2524608000
    },
    {
      "id": 23,
      "scenario_id": 0,
      "disp_order": 3,
      "group_id": 3,
      "rank": 1,
      "chara_data_id": 0,
      "user_show": 1,
      "receive_condition_type": 3,
      "start_date": 1483228800,
      "end_date": 2524608000
    },
    {
      "id": 24,
      "scenario_id": 0,
      "disp_order": 34,
      "group_id": 34,
      "rank": 1,
      "chara_data_id": 0,
      "user_show": 1,
      "receive_condition_type": 3,
      "start_date": 1483228800,
      "end_date": 2524608000
    },
    {
      "id": 25,
      "scenario_id": 0,
      "disp_order": 35,
      "group_id": 35,
      "rank": 1,
      "chara_data_id": 0,
      "user_show": 1,
      "receive_condition_type": 3,
      "start_date": 1483228800,
      "end_date": 2524608000
    },
    {
      "id": 26,
      "scenario_id": 0,
      "disp_order": 2026,
      "group_id": 2026,
      "rank": 2,
      "chara_data_id": 0,
      "user_show": 1,
      "receive_condition_type": 3,
      "start_date": 1483228800,
      "end_date": 2524608000
    },
    {
      "id": 27,
      "scenario_id": 0,
      "disp_order": 2028,
      "group_id": 2028,
      "rank": 2,
      "chara_data_id": 0,
      "user_show": 1,
      "receive_condition_type": 3,
      "start_date": 1483228800,
      "end_date": 2524608000
    },
    {
      "id": 28,
      "scenario_id": 0,
      "disp_order": 2023,
      "group_id": 2023,
      "rank": 2,
      "chara_data_id": 0,
      "user_show": 1,
      "receive_condition_type": 3,
      "start_date": 1483228800,
      "end_date": 2524608000
    },
    {
      "id": 29,
      "scenario_id": 0,
      "disp_order": 2024,
      "group_id": 2024,
      "rank": 2,
      "chara_data_id": 0,
      "user_show": 1,
      "receive_condition_type": 3,
      "start_date": 1483228800,
      "end_date": 2524608000
    },
    {
      "id": 30,
      "scenario_id": 0,
      "disp_order": 2029,
      "group_id": 2029,
      "rank": 2,
      "chara_data_id": 0,
      "user_show": 1,
      "receive_condition_type": 3,
      "start_date": 1483228800,
      "end_date": 2524608000
    },
    {
      "id": 31,
      "scenario_id": 0,
      "disp_order": 2033,
      "group_id": 2033,
      "rank": 2,
      "chara_data_id": 0,
      "user_show": 1,
      "receive_condition_type": 3,
      "start_date": 1483228800,
      "end_date": 2524608000
    },
    {
      "id": 32,
      "scenario_id": 0,
      "disp_order": 2021,
      "group_id": 2021,
      "rank": 2,
      "chara_data_id": 0,
      "user_show": 1,
      "receive_condition_type": 3,
      "start_date": 1483228800,
      "end_date": 2524608000
    },
    {
      "id": 33,
      "scenario_id": 0,
      "disp_order": 18,
      "group_id": 18,
      "rank": 1,
      "chara_data_id": 0,
      "user_show": 1,
      "receive_condition_type": 3,
      "start_date": 1483228800,
      "end_date": 2524608000
    },
    {
      "id": 34,
      "scenario_id": 0,
      "disp_order": 38,
      "group_id": 38,
      "rank": 1,
      "chara_data_id": 0,
      "user_show": 1,
      "receive_condition_type": 3,
      "start_date": 1483228800,
      "end_date": 2524608000
    },
    {
      "id": 35,
      "scenario_id": 0,
      "disp_order": 32,
      "group_id": 32,
      "rank": 1,
      "chara_data_id": 0,
      "user_show": 1,
      "receive_condition_type": 3,
      "start_date": 1483228800,
      "end_date": 2524608000
    },
    {
      "id": 36,
      "scenario_id": 0,
      "disp_order": 20,
      "group_id": 20,
      "rank": 1,
      "chara_data_id": 0,
      "user_show": 1,
      "receive_condition_type": 3,
      "start_date": 1483228800,
      "end_date": 2524608000
    },
    {
      "id": 37,
      "scenario_id": 0,
      "disp_order": 2032,
      "group_id": 2032,
      "rank": 2,
      "chara_data_id": 0,
      "user_show": 1,
      "receive_condition_type": 3,
      "start_date": 1483228800,
      "end_date": 2524608000
    },
    {
      "id": 38,
      "scenario_id": 0,
      "disp_order": 2012,
      "group_id": 2012,
      "rank": 2,
      "chara_data_id": 0,
      "user_show": 1,
      "receive_condition_type": 3,
      "start_date": 1483228800,
      "end_date": 2524608000
    },
    {
      "id": 39,
      "scenario_id": 0,
      "disp_order": 2034,
      "group_id": 2034,
      "rank": 2,
      "chara_data_id": 0,
      "user_show": 1,
      "receive_condition_type": 3,
      "start_date": 1483228800,
      "end_date": 2524608000
    },
    {
      "id": 40,
      "scenario_id": 0,
      "disp_order": 43,
      "group_id": 43,
      "rank": 1,
      "chara_data_id": 0,
      "user_show": 1,
      "receive_condition_type": 3,
      "start_date": 1483228800,
      "end_date": 2524608000
    },
    {
      "id": 41,
      "scenario_id": 0,
      "disp_order": 2010,
      "group_id": 2010,
      "rank": 2,
      "chara_data_id": 0,
      "user_show": 1,
      "receive_condition_type": 3,
      "start_date": 1483228800,
      "end_date": 2524608000
    },
    {
      "id": 42,
      "scenario_id": 0,
      "disp_order": 37,
      "group_id": 37,
      "rank": 1,
      "chara_data_id": 0,
      "user_show": 1,
      "receive_condition_type": 1,
      "start_date": 1483228800,
      "end_date": 2524608000
    },
    {
      "id": 43,
      "scenario_id": 0,
      "disp_order": 3018,
      "group_id": 3018,
      "rank": 3,
      "chara_data_id": 1018,
      "user_show": 1,
      "receive_condition_type": 3,
      "start_date": 1483228800,
      "end_date": 2524608000
    },
    {
      "id": 44,
      "scenario_id": 0,
      "disp_order": 3040,
      "group_id": 3040,
      "rank": 3,
      "chara_data_id": 1040,
      "user_show": 1,
      "receive_condition_type": 1,
      "start_date": 1759874400,
      "end_date": 2524608000
    },
    {
      "id": 45,
      "scenario_id": 0,
      "disp_order": 3030,
      "group_id": 3030,
      "rank": 3,
      "chara_data_id": 1030,
      "user_show": 1,
      "receive_condition_type": 1,
      "start_date": 1483228800,
      "end_date": 2524608000
    },
    {
      "id": 46,
      "scenario_id": 0,
      "disp_order": 3037,
      "group_id": 3037,
      "rank": 3,
      "chara_data_id": 1037,
      "user_show": 1,
      "receive_condition_type": 1,
      "start_date": 1761861600,
      "end_date": 2524608000
    },
    {
      "id": 47,
      "scenario_id": 0,
      "disp_order": 3035,
      "group_id": 3035,
      "rank": 3,
      "chara_data_id": 1035,
      "user_show": 1,
      "receive_condition_type": 3,
      "start_date": 1483228800,
      "end_date": 2524608000
    },
    {
      "id": 48,
      "scenario_id": 0,
      "disp_order": 3032,
      "group_id": 3032,
      "rank": 3,
      "chara_data_id": 1032,
      "user_show": 1,
      "receive_condition_type": 3,
      "start_date": 1483228800,
      "end_date": 2524608000
    },
    {
      "id": 49,
      "scenario_id": 0,
      "disp_order": 5023,
      "group_id": 5023,
      "rank": 3,
      "chara_data_id": 0,
      "user_show": 1,
      "receive_condition_type": 3,
      "start_date": 1483228800,
      "end_date": 2524608000
    },
    {
      "id": 50,
      "scenario_id": 0,
      "disp_order": 2015,
      "group_id": 2015,
      "rank": 2,
      "chara_data_id": 0,
      "user_show": 1,
      "receive_condition_type": 3,
      "start_date": 1483228800,
      "end_date": 2524608000
    },
    {
      "id": 51,
      "scenario_id": 0,
      "disp_order": 2037,
      "group_id": 2037,
      "rank": 2,
      "chara_data_id": 0,
      "user_show": 1,
      "receive_condition_type": 3,
      "start_date": 1483228800,
      "end_date": 2524608000
    },
    {
      "id": 52,
      "scenario_id": 0,
      "disp_order": 2025,
      "group_id": 2025,
      "rank": 2,
      "chara_data_id": 0,
      "user_show": 1,
      "receive_condition_type": 3,
      "start_date": 1483228800,
      "end_date": 2524608000
    },
    {
      "id": 54,
      "scenario_id": 0,
      "disp_order": 5024,
      "group_id": 5024,
      "rank": 3,
      "chara_data_id": 0,
      "user_show": 1,
      "receive_condition_type": 2,
      "start_date": 1483228800,
      "end_date": 2524608000
    },
    {
      "id": 55,
      "scenario_id": 0,
      "disp_order": 5022,
      "group_id": 5022,
      "rank": 3,
      "chara_data_id": 0,
      "user_show": 1,
      "receive_condition_type": 3,
      "start_date": 1483228800,
      "end_date": 2524608000
    },
    {
      "id": 56,
      "scenario_id": 0,
      "disp_order": 2013,
      "group_id": 2013,
      "rank": 2,
      "chara_data_id": 0,
      "user_show": 1,
      "receive_condition_type": 3,
      "start_date": 1483228800,
      "end_date": 2524608000
    },
    {
      "id": 57,
      "scenario_id": 0,
      "disp_order": 5008,
      "group_id": 5008,
      "rank": 3,
      "chara_data_id": 0,
      "user_show": 1,
      "receive_condition_type": 3,
      "start_date": 1483228800,
      "end_date": 2524608000
    },
    {
      "id": 58,
      "scenario_id": 0,
      "disp_order": 5011,
      "group_id": 5011,
      "rank": 3,
      "chara_data_id": 0,
      "user_show": 1,
      "receive_condition_type": 3,
      "start_date": 1483228800,
      "end_date": 2524608000
    },
    {
      "id": 59,
      "scenario_id": 0,
      "disp_order": 2036,
      "group_id": 2036,
      "rank": 2,
      "chara_data_id": 0,
      "user_show": 1,
      "receive_condition_type": 3,
      "start_date": 1483228800,
      "end_date": 2524608000
    },
    {
      "id": 60,
      "scenario_id": 0,
      "disp_order": 5010,
      "group_id": 5010,
      "rank": 3,
      "chara_data_id": 0,
      "user_show": 1,
      "receive_condition_type": 3,
      "start_date": 1483228800,
      "end_date": 2524608000
    },
    {
      "id": 61,
      "scenario_id": 0,
      "disp_order": 5020,
      "group_id": 5020,
      "rank": 3,
      "chara_data_id": 0,
      "user_show": 1,
      "receive_condition_type": 2,
      "start_date": 1483228800,
      "end_date": 2524608000
    },
    {
      "id": 62,
      "scenario_id": 0,
      "disp_order": 36,
      "group_id": 36,
      "rank": 1,
      "chara_data_id": 0,
      "user_show": 1,
      "receive_condition_type": 3,
      "start_date": 1483228800,
      "end_date": 2524608000
    },
    {
      "id": 63,
      "scenario_id": 0,
      "disp_order": 5025,
      "group_id": 5025,
      "rank": 3,
      "chara_data_id": 0,
      "user_show": 1,
      "receive_condition_type": 3,
      "start_date": 1483228800,
      "end_date": 2524608000
    },
    {
      "id": 64,
      "scenario_id": 0,
      "disp_order": 5012,
      "group_id": 5012,
      "rank": 3,
      "chara_data_id": 0,
      "user_show": 1,
      "receive_condition_type": 3,
      "start_date": 1483228800,
      "end_date": 2524608000
    },
    {
      "id": 65,
      "scenario_id": 0,
      "disp_order": 5013,
      "group_id": 5013,
      "rank": 3,
      "chara_data_id": 0,
      "user_show": 1,
      "receive_condition_type": 3,
      "start_date": 1483228800,
      "end_date": 2524608000
    },
    {
      "id": 66,
      "scenario_id": 0,
      "disp_order": 3001,
      "group_id": 3001,
      "rank": 3,
      "chara_data_id": 1001,
      "user_show": 1,
      "receive_condition_type": 3,
      "start_date": 1483228800,
      "end_date": 2524608000
    },
    {
      "id": 67,
      "scenario_id": 0,
      "disp_order": 3002,
      "group_id": 3002,
      "rank": 3,
      "chara_data_id": 1002,
      "user_show": 1,
      "receive_condition_type": 3,
      "start_date": 1483228800,
      "end_date": 2524608000
    },
    {
      "id": 68,
      "scenario_id": 0,
      "disp_order": 3014,
      "group_id": 3014,
      "rank": 3,
      "chara_data_id": 1014,
      "user_show": 1,
      "receive_condition_type": 1,
      "start_date": 1483228800,
      "end_date": 2524608000
    },
    {
      "id": 69,
      "scenario_id": 0,
      "disp_order": 3004,
      "group_id": 3004,
      "rank": 3,
      "chara_data_id": 1004,
      "user_show": 1,
      "receive_condition_type": 3,
      "start_date": 1483228800,
      "end_date": 2524608000
    },
    {
      "id": 70,
      "scenario_id": 0,
      "disp_order": 3024,
      "group_id": 3024,
      "rank": 3,
      "chara_data_id": 1024,
      "user_show": 1,
      "receive_condition_type": 3,
      "start_date": 1483228800,
      "end_date": 2524608000
    },
    {
      "id": 71,
      "scenario_id": 0,
      "disp_order": 3041,
      "group_id": 3041,
      "rank": 3,
      "chara_data_id": 1041,
      "user_show": 1,
      "receive_condition_type": 3,
      "start_date": 1483228800,
      "end_date": 2524608000
    },
    {
      "id": 72,
      "scenario_id": 0,
      "disp_order": 3045,
      "group_id": 3045,
      "rank": 3,
      "chara_data_id": 1045,
      "user_show": 1,
      "receive_condition_type": 3,
      "start_date": 1483228800,
      "end_date": 2524608000
    },
    {
      "id": 73,
      "scenario_id": 0,
      "disp_order": 3011,
      "group_id": 3011,
      "rank": 3,
      "chara_data_id": 1011,
      "user_show": 1,
      "receive_condition_type": 3,
      "start_date": 1483228800,
      "end_date": 2524608000
    },
    {
      "id": 74,
      "scenario_id": 0,
      "disp_order": 3008,
      "group_id": 3008,
      "rank": 3,
      "chara_data_id": 1008,
      "user_show": 1,
      "receive_condition_type": 3,
      "start_date": 1483228800,
      "end_date": 2524608000
    },
    {
      "id": 75,
      "scenario_id": 0,
      "disp_order": 3009,
      "group_id": 3009,
      "rank": 3,
      "chara_data_id": 1009,
      "user_show": 1,
      "receive_condition_type": 3,
      "start_date": 1483228800,
      "end_date": 2524608000
    },
    {
      "id": 76,
      "scenario_id": 0,
      "disp_order": 3003,
      "group_id": 3003,
      "rank": 3,
      "chara_data_id": 1003,
      "user_show": 1,
      "receive_condition_type": 3,
      "start_date": 1483228800,
      "end_date": 2524608000
    },
    {
      "id": 77,
      "scenario_id": 0,
      "disp_order": 3007,
      "group_id": 3007,
      "rank": 3,
      "chara_data_id": 1007,
      "user_show": 1,
      "receive_condition_type": 3,
      "start_date": 1483228800,
      "end_date": 2524608000
    },
    {
      "id": 78,
      "scenario_id": 0,
      "disp_order": 3017,
      "group_id": 3017,
      "rank": 3,
      "chara_data_id": 1017,
      "user_show": 1,
      "receive_condition_type": 3,
      "start_date": 1483228800,
      "end_date": 2524608000
    },
    {
      "id": 79,
      "scenario_id": 0,
      "disp_order": 3056,
      "group_id": 3056,
      "rank": 3,
      "chara_data_id": 1056,
      "user_show": 1,
      "receive_condition_type": 3,
      "start_date": 1483228800,
      "end_date": 2524608000
    },
    {
      "id": 80,
      "scenario_id": 0,
      "disp_order": 3005,
      "group_id": 3005,
      "rank": 3,
      "chara_data_id": 1005,
      "user_show": 1,
      "receive_condition_type": 3,
      "start_date": 1759442400,
      "end_date": 2524608000
    },
    {
      "id": 81,
      "scenario_id": 0,
      "disp_order": 3060,
      "group_id": 3060,
      "rank": 3,
      "chara_data_id": 1060,
      "user_show": 1,
      "receive_condition_type": 3,
      "start_date": 1483228800,
      "end_date": 2524608000
    },
    {
      "id": 82,
      "scenario_id": 0,
      "disp_order": 3027,
      "group_id": 3027,
      "rank": 3,
      "chara_data_id": 1027,
      "user_show": 1,
      "receive_condition_type": 3,
      "start_date": 1483228800,
      "end_date": 2524608000
    },
    {
      "id": 83,
      "scenario_id": 0,
      "disp_order": 3010,
      "group_id": 3010,
      "rank": 3,
      "chara_data_id": 1010,
      "user_show": 1,
      "receive_condition_type": 3,
      "start_date": 1483228800,
      "end_date": 2524608000
    },
    {
      "id": 84,
      "scenario_id": 0,
      "disp_order": 3006,
      "group_id": 3006,
      "rank": 3,
      "chara_data_id": 1006,
      "user_show": 1,
      "receive_condition_type": 3,
      "start_date": 1483228800,
      "end_date": 2524608000
    },
    {
      "id": 85,
      "scenario_id": 0,
      "disp_order": 3012,
      "group_id": 3012,
      "rank": 3,
      "chara_data_id": 1012,
      "user_show": 1,
      "receive_condition_type": 3,
      "start_date": 1758146400,
      "end_date": 2524608000
    },
    {
      "id": 86,
      "scenario_id": 0,
      "disp_order": 3015,
      "group_id": 3015,
      "rank": 3,
      "chara_data_id": 1015,
      "user_show": 1,
      "receive_condition_type": 3,
      "start_date": 1750897800,
      "end_date": 2524608000
    },
    {
      "id": 87,
      "scenario_id": 0,
      "disp_order": 3026,
      "group_id": 3026,
      "rank": 3,
      "chara_data_id": 1026,
      "user_show": 1,
      "receive_condition_type": 3,
      "start_date": 1751493600,
      "end_date": 2524608000
    },
    {
      "id": 88,
      "scenario_id": 0,
      "disp_order": 3046,
      "group_id": 3046,
      "rank": 3,
      "chara_data_id": 1046,
      "user_show": 1,
      "receive_condition_type": 3,
      "start_date": 1754949600,
      "end_date": 2524608000
    },
    {
      "id": 89,
      "scenario_id": 0,
      "disp_order": 3038,
      "group_id": 3038,
      "rank": 3,
      "chara_data_id": 1038,
      "user_show": 1,
      "receive_condition_type": 3,
      "start_date": 1753653600,
      "end_date": 2524608000
    },
    {
      "id": 90,
      "scenario_id": 0,
      "disp_order": 2009,
      "group_id": 2009,
      "rank": 2,
      "chara_data_id": 0,
      "user_show": 1,
      "receive_condition_type": 3,
      "start_date": 1483228800,
      "end_date": 2524608000
    },
    {
      "id": 91,
      "scenario_id": 0,
      "disp_order": 5009,
      "group_id": 5009,
      "rank": 3,
      "chara_data_id": 0,
      "user_show": 1,
      "receive_condition_type": 3,
      "start_date": 1483228800,
      "end_date": 2524608000
    },
    {
      "id": 92,
      "scenario_id": 0,
      "disp_order": 46,
      "group_id": 46,
      "rank": 1,
      "chara_data_id": 0,
      "user_show": 1,
      "receive_condition_type": 3,
      "start_date": 1483228800,
      "end_date": 2524608000
    },
    {
      "id": 97,
      "scenario_id": 0,
      "disp_order": 5001,
      "group_id": 5001,
      "rank": 3,
      "chara_data_id": 0,
      "user_show": 1,
      "receive_condition_type": 3,
      "start_date": 1483228800,
      "end_date": 2524608000
    },
    {
      "id": 98,
      "scenario_id": 0,
      "disp_order": 5026,
      "group_id": 5026,
      "rank": 3,
      "chara_data_id": 0,
      "user_show": 1,
      "receive_condition_type": 3,
      "start_date": 1483228800,
      "end_date": 2524608000
    },
    {
      "id": 99,
      "scenario_id": 0,
      "disp_order": 2027,
      "group_id": 2027,
      "rank": 2,
      "chara_data_id": 0,
      "user_show": 1,
      "receive_condition_type": 3,
      "start_date": 1483228800,
      "end_date": 2524608000
    },
    {
      "id": 100,
      "scenario_id": 0,
      "disp_order": 2,
      "group_id": 2,
      "rank": 1,
      "chara_data_id": 0,
      "user_show": 1,
      "receive_condition_type": 3,
      "start_date": 1483228800,
      "end_date": 2524608000
    },
    {
      "id": 101,
      "scenario_id": 0,
      "disp_order": 1,
      "group_id": 1,
      "rank": 1,
      "chara_data_id": 0,
      "user_show": 1,
      "receive_condition_type": 3,
      "start_date": 1483228800,
      "end_date": 2524608000
    },
    {
      "id": 102,
      "scenario_id": 0,
      "disp_order": 5,
      "group_id": 5,
      "rank": 1,
      "chara_data_id": 0,
      "user_show": 1,
      "receive_condition_type": 3,
      "start_date": 1483228800,
      "end_date": 2524608000
    },
    {
      "id": 103,
      "scenario_id": 0,
      "disp_order": 2019,
      "group_id": 2019,
      "rank": 2,
      "chara_data_id": 0,
      "user_show": 1,
      "receive_condition_type": 3,
      "start_date": 1483228800,
      "end_date": 2524608000
    },
    {
      "id": 104,
      "scenario_id": 0,
      "disp_order": 2030,
      "group_id": 2030,
      "rank": 2,
      "chara_data_id": 0,
      "user_show": 1,
      "receive_condition_type": 3,
      "start_date": 1483228800,
      "end_date": 2524608000
    },
    {
      "id": 105,
      "scenario_id": 0,
      "disp_order": 2016,
      "group_id": 2016,
      "rank": 2,
      "chara_data_id": 0,
      "user_show": 1,
      "receive_condition_type": 3,
      "start_date": 1483228800,
      "end_date": 2524608000
    },
    {
      "id": 106,
      "scenario_id": 0,
      "disp_order": 2017,
      "group_id": 2017,
      "rank": 2,
      "chara_data_id": 0,
      "user_show": 1,
      "receive_condition_type": 3,
      "start_date": 1483228800,
      "end_date": 2524608000
    },
    {
      "id": 107,
      "scenario_id": 0,
      "disp_order": 2005,
      "group_id": 2005,
      "rank": 2,
      "chara_data_id": 0,
      "user_show": 1,
      "receive_condition_type": 3,
      "start_date": 1483228800,
      "end_date": 2524608000
    },
    {
      "id": 108,
      "scenario_id": 0,
      "disp_order": 2022,
      "group_id": 2022,
      "rank": 2,
      "chara_data_id": 0,
      "user_show": 1,
      "receive_condition_type": 2,
      "start_date": 1483228800,
      "end_date": 2524608000
    },
    {
      "id": 109,
      "scenario_id": 0,
      "disp_order": 2018,
      "group_id": 2018,
      "rank": 2,
      "chara_data_id": 0,
      "user_show": 1,
      "receive_condition_type": 3,
      "start_date": 1483228800,
      "end_date": 2524608000
    },
    {
      "id": 110,
      "scenario_id": 0,
      "disp_order": 2020,
      "group_id": 2020,
      "rank": 2,
      "chara_data_id": 0,
      "user_show": 1,
      "receive_condition_type": 3,
      "start_date": 1483228800,
      "end_date": 2524608000
    },
    {
      "id": 112,
      "scenario_id": 0,
      "disp_order": 2008,
      "group_id": 2008,
      "rank": 2,
      "chara_data_id": 0,
      "user_show": 1,
      "receive_condition_type": 3,
      "start_date": 1483228800,
      "end_date": 2524608000
    },
    {
      "id": 113,
      "scenario_id": 0,
      "disp_order": 5015,
      "group_id": 5015,
      "rank": 3,
      "chara_data_id": 0,
      "user_show": 1,
      "receive_condition_type": 3,
      "start_date": 1483228800,
      "end_date": 2524608000
    },
    {
      "id": 114,
      "scenario_id": 0,
      "disp_order": 5021,
      "group_id": 5021,
      "rank": 3,
      "chara_data_id": 0,
      "user_show": 1,
      "receive_condition_type": 3,
      "start_date": 1483228800,
      "end_date": 2524608000
    },
    {
      "id": 115,
      "scenario_id": 0,
      "disp_order": 2011,
      "group_id": 2011,
      "rank": 2,
      "chara_data_id": 0,
      "user_show": 1,
      "receive_condition_type": 1,
      "start_date": 1483228800,
      "end_date": 2524608000
    },
    {
      "id": 116,
      "scenario_id": 0,
      "disp_order": 2006,
      "group_id": 2006,
      "rank": 2,
      "chara_data_id": 0,
      "user_show": 1,
      "receive_condition_type": 3,
      "start_date": 1483228800,
      "end_date": 2524608000
    },
    {
      "id": 117,
      "scenario_id": 0,
      "disp_order": 5007,
      "group_id": 5007,
      "rank": 3,
      "chara_data_id": 0,
      "user_show": 1,
      "receive_condition_type": 3,
      "start_date": 1483228800,
      "end_date": 2524608000
    },
    {
      "id": 118,
      "scenario_id": 0,
      "disp_order": 2014,
      "group_id": 2014,
      "rank": 2,
      "chara_data_id": 0,
      "user_show": 1,
      "receive_condition_type": 3,
      "start_date": 1483228800,
      "end_date": 2524608000
    },
    {
      "id": 119,
      "scenario_id": 0,
      "disp_order": 2007,
      "group_id": 2007,
      "rank": 2,
      "chara_data_id": 0,
      "user_show": 1,
      "receive_condition_type": 3,
      "start_date": 1483228800,
      "end_date": 2524608000
    },
    {
      "id": 120,
      "scenario_id": 0,
      "disp_order": 25,
      "group_id": 25,
      "rank": 1,
      "chara_data_id": 0,
      "user_show": 1,
      "receive_condition_type": 3,
      "start_date": 1483228800,
      "end_date": 2524608000
    },
    {
      "id": 121,
      "scenario_id": 0,
      "disp_order": 24,
      "group_id": 24,
      "rank": 1,
      "chara_data_id": 0,
      "user_show": 1,
      "receive_condition_type": 3,
      "start_date": 1483228800,
      "end_date": 2524608000
    },
    {
      "id": 122,
      "scenario_id": 0,
      "disp_order": 26,
      "group_id": 26,
      "rank": 1,
      "chara_data_id": 0,
      "user_show": 1,
      "receive_condition_type": 3,
      "start_date": 1483228800,
      "end_date": 2524608000
    },
    {
      "id": 123,
      "scenario_id": 0,
      "disp_order": 28,
      "group_id": 28,
      "rank": 1,
      "chara_data_id": 0,
      "user_show": 1,
      "receive_condition_type": 3,
      "start_date": 1483228800,
      "end_date": 2524608000
    },
    {
      "id": 124,
      "scenario_id": 0,
      "disp_order": 27,
      "group_id": 27,
      "rank": 1,
      "chara_data_id": 0,
      "user_show": 1,
      "receive_condition_type": 3,
      "start_date": 1483228800,
      "end_date": 2524608000
    },
    {
      "id": 125,
      "scenario_id": 0,
      "disp_order": 21,
      "group_id": 21,
      "rank": 1,
      "chara_data_id": 0,
      "user_show": 1,
      "receive_condition_type": 3,
      "start_date": 1483228800,
      "end_date": 2524608000
    },
    {
      "id": 126,
      "scenario_id": 0,
      "disp_order": 3061,
      "group_id": 3061,
      "rank": 3,
      "chara_data_id": 1061,
      "user_show": 1,
      "receive_condition_type": 3,
      "start_date": 1483228800,
      "end_date": 2524608000
    },
    {
      "id": 127,
      "scenario_id": 0,
      "disp_order": 3013,
      "group_id": 3013,
      "rank": 3,
      "chara_data_id": 1013,
      "user_show": 1,
      "receive_condition_type": 3,
      "start_date": 1483228800,
      "end_date": 2524608000
    },
    {
      "id": 128,
      "scenario_id": 0,
      "disp_order": 45,
      "group_id": 45,
      "rank": 1,
      "chara_data_id": 0,
      "user_show": 1,
      "receive_condition_type": 3,
      "start_date": 1483228800,
      "end_date": 2524608000
    },
    {
      "id": 129,
      "scenario_id": 0,
      "disp_order": 44,
      "group_id": 44,
      "rank": 1,
      "chara_data_id": 0,
      "user_show": 1,
      "receive_condition_type": 3,
      "start_date": 1483228800,
      "end_date": 2524608000
    },
    {
      "id": 130,
      "scenario_id": 0,
      "disp_order": 2038,
      "group_id": 2038,
      "rank": 2,
      "chara_data_id": 0,
      "user_show": 1,
      "receive_condition_type": 3,
      "start_date": 1483228800,
      "end_date": 2524608000
    },
    {
      "id": 131,
      "scenario_id": 0,
      "disp_order": 39,
      "group_id": 39,
      "rank": 1,
      "chara_data_id": 0,
      "user_show": 1,
      "receive_condition_type": 3,
      "start_date": 1483228800,
      "end_date": 2524608000
    },
    {
      "id": 132,
      "scenario_id": 0,
      "disp_order": 30,
      "group_id": 30,
      "rank": 1,
      "chara_data_id": 0,
      "user_show": 1,
      "receive_condition_type": 1,
      "start_date": 1483228800,
      "end_date": 2524608000
    },
    {
      "id": 133,
      "scenario_id": 0,
      "disp_order": 19,
      "group_id": 19,
      "rank": 1,
      "chara_data_id": 0,
      "user_show": 1,
      "receive_condition_type": 3,
      "start_date": 1483228800,
      "end_date": 2524608000
    },
    {
      "id": 134,
      "scenario_id": 0,
      "disp_order": 12,
      "group_id": 12,
      "rank": 1,
      "chara_data_id": 0,
      "user_show": 1,
      "receive_condition_type": 3,
      "start_date": 1483228800,
      "end_date": 2524608000
    },
    {
      "id": 135,
      "scenario_id": 0,
      "disp_order": 5006,
      "group_id": 5006,
      "rank": 3,
      "chara_data_id": 0,
      "user_show": 1,
      "receive_condition_type": 3,
      "start_date": 1483228800,
      "end_date": 2524608000
    },
    {
      "id": 136,
      "scenario_id": 0,
      "disp_order": 5004,
      "group_id": 5004,
      "rank": 3,
      "chara_data_id": 0,
      "user_show": 1,
      "receive_condition_type": 3,
      "start_date": 1483228800,
      "end_date": 2524608000
    },
    {
      "id": 137,
      "scenario_id": 0,
      "disp_order": 5005,
      "group_id": 5005,
      "rank": 3,
      "chara_data_id": 0,
      "user_show": 1,
      "receive_condition_type": 3,
      "start_date": 1483228800,
      "end_date": 2524608000
    },
    {
      "id": 138,
      "scenario_id": 0,
      "disp_order": 5002,
      "group_id": 5002,
      "rank": 3,
      "chara_data_id": 0,
      "user_show": 1,
      "receive_condition_type": 3,
      "start_date": 1483228800,
      "end_date": 2524608000
    },
    {
      "id": 139,
      "scenario_id": 0,
      "disp_order": 5003,
      "group_id": 5003,
      "rank": 3,
      "chara_data_id": 0,
      "user_show": 1,
      "receive_condition_type": 3,
      "start_date": 1483228800,
      "end_date": 2524608000
    },
    {
      "id": 140,
      "scenario_id": 0,
      "disp_order": 2031,
      "group_id": 2031,
      "rank": 2,
      "chara_data_id": 0,
      "user_show": 1,
      "receive_condition_type": 3,
      "start_date": 1483228800,
      "end_date": 2524608000
    },
    {
      "id": 141,
      "scenario_id": 0,
      "disp_order": 11,
      "group_id": 11,
      "rank": 1,
      "chara_data_id": 0,
      "user_show": 1,
      "receive_condition_type": 3,
      "start_date": 1483228800,
      "end_date": 2524608000
    },
    {
      "id": 142,
      "scenario_id": 0,
      "disp_order": 2004,
      "group_id": 2004,
      "rank": 2,
      "chara_data_id": 0,
      "user_show": 1,
      "receive_condition_type": 3,
      "start_date": 1483228800,
      "end_date": 2524608000
    },
    {
      "id": 143,
      "scenario_id": 0,
      "disp_order": 2003,
      "group_id": 2003,
      "rank": 2,
      "chara_data_id": 0,
      "user_show": 1,
      "receive_condition_type": 1,
      "start_date": 1483228800,
      "end_date": 2524608000
    },
    {
      "id": 144,
      "scenario_id": 0,
      "disp_order": 2001,
      "group_id": 2001,
      "rank": 2,
      "chara_data_id": 0,
      "user_show": 1,
      "receive_condition_type": 1,
      "start_date": 1483228800,
      "end_date": 2524608000
    },
    {
      "id": 145,
      "scenario_id": 0,
      "disp_order": 5019,
      "group_id": 5019,
      "rank": 3,
      "chara_data_id": 0,
      "user_show": 1,
      "receive_condition_type": 3,
      "start_date": 1483228800,
      "end_date": 2524608000
    },
    {
      "id": 146,
      "scenario_id": 0,
      "disp_order": 5017,
      "group_id": 5017,
      "rank": 3,
      "chara_data_id": 0,
      "user_show": 1,
      "receive_condition_type": 3,
      "start_date": 1483228800,
      "end_date": 2524608000
    },
    {
      "id": 147,
      "scenario_id": 0,
      "disp_order": 2002,
      "group_id": 2002,
      "rank": 2,
      "chara_data_id": 0,
      "user_show": 1,
      "receive_condition_type": 1,
      "start_date": 1483228800,
      "end_date": 2524608000
    },
    {
      "id": 148,
      "scenario_id": 0,
      "disp_order": 5018,
      "group_id": 5018,
      "rank": 3,
      "chara_data_id": 0,
      "user_show": 1,
      "receive_condition_type": 3,
      "start_date": 1483228800,
      "end_date": 2524608000
    },
    {
      "id": 149,
      "scenario_id": 0,
      "disp_order": 5016,
      "group_id": 5016,
      "rank": 3,
      "chara_data_id": 0,
      "user_show": 1,
      "receive_condition_type": 3,
      "start_date": 1483228800,
      "end_date": 2524608000
    },
    {
      "id": 150,
      "scenario_id": 0,
      "disp_order": 5014,
      "group_id": 5014,
      "rank": 3,
      "chara_data_id": 0,
      "user_show": 1,
      "receive_condition_type": 3,
      "start_date": 1483228800,
      "end_date": 2524608000
    },
    {
      "id": 151,
      "scenario_id": 0,
      "disp_order": 3023,
      "group_id": 3023,
      "rank": 3,
      "chara_data_id": 1023,
      "user_show": 1,
      "receive_condition_type": 2,
      "start_date": 1752184800,
      "end_date": 2524608000
    },
    {
      "id": 152,
      "scenario_id": 2,
      "disp_order": 1002,
      "group_id": 1002,
      "rank": 2,
      "chara_data_id": 0,
      "user_show": 1,
      "receive_condition_type": 2,
      "start_date": 1762466400,
      "end_date": 2524608000
    },
    {
      "id": 153,
      "scenario_id": 2,
      "disp_order": 1001,
      "group_id": 1001,
      "rank": 2,
      "chara_data_id": 0,
      "user_show": 1,
      "receive_condition_type": 2,
      "start_date": 1762466400,
      "end_date": 2524608000
    },
    {
      "id": 154,
      "scenario_id": 2,
      "disp_order": 4001,
      "group_id": 4001,
      "rank": 3,
      "chara_data_id": 0,
      "user_show": 1,
      "receive_condition_type": 3,
      "start_date": 1762466400,
      "end_date": 2524608000
    },
    {
      "id": 155,
      "scenario_id": 2,
      "disp_order": 4002,
      "group_id": 4002,
      "rank": 3,
      "chara_data_id": 0,
      "user_show": 1,
      "receive_condition_type": 2,
      "start_date": 1762466400,
      "end_date": 2524608000
    },
    {
      "id": 160,
      "scenario_id": 0,
      "disp_order": 3050,
      "group_id": 3050,
      "rank": 3,
      "chara_data_id": 1050,
      "user_show": 1,
      "receive_condition_type": 3,
      "start_date": 1754258400,
      "end_date": 2524608000
    },
    {
      "id": 161,
      "scenario_id": 0,
      "disp_order": 3016,
      "group_id": 3016,
      "rank": 3,
      "chara_data_id": 1016,
      "user_show": 1,
      "receive_condition_type": 3,
      "start_date": 1755727200,
      "end_date": 2524608000
    },
    {
      "id": 162,
      "scenario_id": 2,
      "disp_order": 4003,
      "group_id": 4003,
      "rank": 3,
      "chara_data_id": 0,
      "user_show": 1,
      "receive_condition_type": 3,
      "start_date": 1762466400,
      "end_date": 2524608000
    },
    {
      "id": 163,
      "scenario_id": 2,
      "disp_order": 4004,
      "group_id": 4004,
      "rank": 3,
      "chara_data_id": 0,
      "user_show": 1,
      "receive_condition_type": 3,
      "start_date": 1762466400,
      "end_date": 2524608000
    },
    {
      "id": 164,
      "scenario_id": 0,
      "disp_order": 3020,
      "group_id": 3020,
      "rank": 3,
      "chara_data_id": 1020,
      "user_show": 1,
      "receive_condition_type": 3,
      "start_date": 1757282400,
      "end_date": 2524608000
    },
    {
      "id": 165,
      "scenario_id": 0,
      "disp_order": 3058,
      "group_id": 3058,
      "rank": 3,
      "chara_data_id": 1058,
      "user_show": 1,
      "receive_condition_type": 3,
      "start_date": 1761084000,
      "end_date": 2524608000
    },
    {
      "id": 166,
      "scenario_id": 0,
      "disp_order": 3028,
      "group_id": 3028,
      "rank": 3,
      "chara_data_id": 1028,
      "user_show": 1,
      "receive_condition_type": 3,
      "start_date": 1762898400,
      "end_date": 2524608000
    },
    {
      "id": 167,
      "scenario_id": 0,
      "disp_order": 3019,
      "group_id": 3019,
      "rank": 3,
      "chara_data_id": 1019,
      "user_show": 1,
      "receive_condition_type": 3,
      "start_date": 1763589600,
      "end_date": 2524608000
    },
    {
      "id": 168,
      "scenario_id": 0,
      "disp_order": 3039,
      "group_id": 3039,
      "rank": 3,
      "chara_data_id": 1039,
      "user_show": 1,
      "receive_condition_type": 3,
      "start_date": 1764626400,
      "end_date": 2524608000
    },
    {
      "id": 169,
      "scenario_id": 0,
      "disp_order": 3025,
      "group_id": 3025,
      "rank": 3,
      "chara_data_id": 1025,
      "user_show": 1,
      "receive_condition_type": 3,
      "start_date": 1765231200,
      "end_date": 2524608000
    },
    {
      "id": 170,
      "scenario_id": 0,
      "disp_order": 3048,
      "group_id": 3048,
      "rank": 3,
      "chara_data_id": 1048,
      "user_show": 1,
      "receive_condition_type": 3,
      "start_date": 1766095200,
      "end_date": 2524608000
    },
    {
      "id": 171,
      "scenario_id": 0,
      "disp_order": 3059,
      "group_id": 3059,
      "rank": 3,
      "chara_data_id": 1059,
      "user_show": 1,
      "receive_condition_type": 3,
      "start_date": 1766959200,
      "end_date": 2524608000
    },
    {
      "id": 172,
      "scenario_id": 0,
      "disp_order": 3022,
      "group_id": 3022,
      "rank": 3,
      "chara_data_id": 1022,
      "user_show": 1,
      "receive_condition_type": 3,
      "start_date": 1768514400,
      "end_date": 2524608000
    },
    {
      "id": 173,
      "scenario_id": 0,
      "disp_order": 3021,
      "group_id": 3021,
      "rank": 3,
      "chara_data_id": 1021,
      "user_show": 1,
      "receive_condition_type": 3,
      "start_date": 1769119200,
      "end_date": 2524608000
    },
    {
      "id": 174,
      "scenario_id": 0,
      "disp_order": 3069,
      "group_id": 3069,
      "rank": 3,
      "chara_data_id": 1069,
      "user_show": 1,
      "receive_condition_type": 3,
      "start_date": 1770847200,
      "end_date": 2524608000
    },
    {
      "id": 175,
      "scenario_id": 0,
      "disp_order": 3071,
      "group_id": 3071,
      "rank": 3,
      "chara_data_id": 1071,
      "user_show": 1,
      "receive_condition_type": 1,
      "start_date": 1772056800,
      "end_date": 2524608000
    },
    {
      "id": 176,
      "scenario_id": 0,
      "disp_order": 3033,
      "group_id": 3033,
      "rank": 3,
      "chara_data_id": 1033,
      "user_show": 1,
      "receive_condition_type": 3,
      "start_date": 1772748000,
      "end_date": 2524608000
    },
    {
      "id": 177,
      "scenario_id": 0,
      "disp_order": 3062,
      "group_id": 3062,
      "rank": 3,
      "chara_data_id": 1062,
      "user_show": 1,
      "receive_condition_type": 3,
      "start_date": 1773352800,
      "end_date": 2524608000
    },
    {
      "id": 178,
      "scenario_id": 0,
      "disp_order": 3068,
      "group_id": 3068,
      "rank": 3,
      "chara_data_id": 1068,
      "user_show": 1,
      "receive_condition_type": 3,
      "start_date": 1773352800,
      "end_date": 2524608000
    },
    {
      "id": 179,
      "scenario_id": 0,
      "disp_order": 3067,
      "group_id": 3067,
      "rank": 3,
      "chara_data_id": 1067,
      "user_show": 1,
      "receive_condition_type": 3,
      "start_date": 1774216800,
      "end_date": 2524608000
    },
    {
      "id": 180,
      "scenario_id": 4,
      "disp_order": 4005,
      "group_id": 4005,
      "rank": 3,
      "chara_data_id": 0,
      "user_show": 1,
      "receive_condition_type": 1,
      "start_date": 1773352800,
      "end_date": 2524608000
    },
    {
      "id": 181,
      "scenario_id": 4,
      "disp_order": 4006,
      "group_id": 4006,
      "rank": 3,
      "chara_data_id": 0,
      "user_show": 1,
      "receive_condition_type": 1,
      "start_date": 1773352800,
      "end_date": 2524608000
    },
    {
      "id": 182,
      "scenario_id": 4,
      "disp_order": 4007,
      "group_id": 4007,
      "rank": 3,
      "chara_data_id": 0,
      "user_show": 1,
      "receive_condition_type": 1,
      "start_date": 1773352800,
      "end_date": 2524608000
    },
    {
      "id": 183,
      "scenario_id": 0,
      "disp_order": 4008,
      "group_id": 4008,
      "rank": 3,
      "chara_data_id": 0,
      "user_show": 1,
      "receive_condition_type": 1,
      "start_date": 1773352800,
      "end_date": 2524608000
    },
    {
      "id": 184,
      "scenario_id": 4,
      "disp_order": 1003,
      "group_id": 1003,
      "rank": 2,
      "chara_data_id": 0,
      "user_show": 1,
      "receive_condition_type": 1,
      "start_date": 1773352800,
      "end_date": 2524608000
    },
    {
      "id": 185,
      "scenario_id": 0,
      "disp_order": 1004,
      "group_id": 1004,
      "rank": 2,
      "chara_data_id": 0,
      "user_show": 1,
      "receive_condition_type": 1,
      "start_date": 1773352800,
      "end_date": 2524608000
    },
    {
      "id": 186,
      "scenario_id": 0,
      "disp_order": 3074,
      "group_id": 3074,
      "rank": 3,
      "chara_data_id": 1074,
      "user_show": 1,
      "receive_condition_type": 3,
      "start_date": 1774562400,
      "end_date": 2524608000
    },
    {
      "id": 187,
      "scenario_id": 4,
      "disp_order": 5027,
      "group_id": 5027,
      "rank": 3,
      "chara_data_id": 0,
      "user_show": 1,
      "receive_condition_type": 3,
      "start_date": 1773352800,
      "end_date": 2524608000
    },
    {
      "id": 188,
      "scenario_id": 4,
      "disp_order": 5028,
      "group_id": 5028,
      "rank": 3,
      "chara_data_id": 0,
      "user_show": 1,
      "receive_condition_type": 3,
      "start_date": 1773352800,
      "end_date": 2524608000
    },
    {
      "id": 189,
      "scenario_id": 4,
      "disp_order": 5029,
      "group_id": 5029,
      "rank": 3,
      "chara_data_id": 0,
      "user_show": 1,
      "receive_condition_type": 3,
      "start_date": 1773352800,
      "end_date": 2524608000
    },
    {
      "id": 190,
      "scenario_id": 4,
      "disp_order": 5030,
      "group_id": 5030,
      "rank": 3,
      "chara_data_id": 0,
      "user_show": 1,
      "receive_condition_type": 3,
      "start_date": 1773352800,
      "end_date": 2524608000
    },
    {
      "id": 191,
      "scenario_id": 4,
      "disp_order": 5031,
      "group_id": 5031,
      "rank": 3,
      "chara_data_id": 0,
      "user_show": 1,
      "receive_condition_type": 3,
      "start_date": 1773352800,
      "end_date": 2524608000
    },
    {
      "id": 192,
      "scenario_id": 4,
      "disp_order": 2039,
      "group_id": 2039,
      "rank": 2,
      "chara_data_id": 0,
      "user_show": 1,
      "receive_condition_type": 3,
      "start_date": 1773352800,
      "end_date": 2524608000
    },
    {
      "id": 193,
      "scenario_id": 4,
      "disp_order": 2040,
      "group_id": 2040,
      "rank": 2,
      "chara_data_id": 0,
      "user_show": 1,
      "receive_condition_type": 3,
      "start_date": 1773352800,
      "end_date": 2524608000
    },
    {
      "id": 194,
      "scenario_id": 4,
      "disp_order": 5032,
      "group_id": 5032,
      "rank": 3,
      "chara_data_id": 0,
      "user_show": 1,
      "receive_condition_type": 3,
      "start_date": 1773352800,
      "end_date": 2524608000
    },
    {
      "id": 195,
      "scenario_id": 4,
      "disp_order": 2041,
      "group_id": 2041,
      "rank": 2,
      "chara_data_id": 0,
      "user_show": 1,
      "receive_condition_type": 3,
      "start_date": 1773352800,
      "end_date": 2524608000
    },
    {
      "id": 196,
      "scenario_id": 4,
      "disp_order": 2042,
      "group_id": 2042,
      "rank": 2,
      "chara_data_id": 0,
      "user_show": 1,
      "receive_condition_type": 3,
      "start_date": 1773352800,
      "end_date": 2524608000
    },
    {
      "id": 197,
      "scenario_id": 4,
      "disp_order": 2043,
      "group_id": 2043,
      "rank": 2,
      "chara_data_id": 0,
      "user_show": 1,
      "receive_condition_type": 3,
      "start_date": 1773352800,
      "end_date": 2524608000
    },
    {
      "id": 198,
      "scenario_id": 4,
      "disp_order": 5033,
      "group_id": 5033,
      "rank": 3,
      "chara_data_id": 0,
      "user_show": 1,
      "receive_condition_type": 3,
      "start_date": 1773352800,
      "end_date": 2524608000
    },
    {
      "id": 199,
      "scenario_id": 4,
      "disp_order": 5034,
      "group_id": 5034,
      "rank": 3,
      "chara_data_id": 0,
      "user_show": 1,
      "receive_condition_type": 3,
      "start_date": 1773352800,
      "end_date": 2524608000
    },
    {
      "id": 200,
      "scenario_id": 4,
      "disp_order": 2044,
      "group_id": 2044,
      "rank": 2,
      "chara_data_id": 0,
      "user_show": 1,
      "receive_condition_type": 3,
      "start_date": 1773352800,
      "end_date": 2524608000
    },
    {
      "id": 201,
      "scenario_id": 4,
      "disp_order": 2045,
      "group_id": 2045,
      "rank": 2,
      "chara_data_id": 0,
      "user_show": 1,
      "receive_condition_type": 3,
      "start_date": 1773352800,
      "end_date": 2524608000
    },
    {
      "id": 202,
      "scenario_id": 4,
      "disp_order": 2046,
      "group_id": 2046,
      "rank": 2,
      "chara_data_id": 0,
      "user_show": 1,
      "receive_condition_type": 3,
      "start_date": 1773352800,
      "end_date": 2524608000
    },
    {
      "id": 203,
      "scenario_id": 4,
      "disp_order": 2047,
      "group_id": 2047,
      "rank": 2,
      "chara_data_id": 0,
      "user_show": 1,
      "receive_condition_type": 3,
      "start_date": 1773352800,
      "end_date": 2524608000
    },
    {
      "id": 204,
      "scenario_id": 4,
      "disp_order": 2048,
      "group_id": 2048,
      "rank": 2,
      "chara_data_id": 0,
      "user_show": 1,
      "receive_condition_type": 3,
      "start_date": 1773352800,
      "end_date": 2524608000
    },
    {
      "id": 205,
      "scenario_id": 4,
      "disp_order": 5035,
      "group_id": 5035,
      "rank": 3,
      "chara_data_id": 0,
      "user_show": 1,
      "receive_condition_type": 3,
      "start_date": 1773352800,
      "end_date": 2524608000
    },
    {
      "id": 206,
      "scenario_id": 4,
      "disp_order": 2049,
      "group_id": 2049,
      "rank": 2,
      "chara_data_id": 0,
      "user_show": 1,
      "receive_condition_type": 3,
      "start_date": 1773352800,
      "end_date": 2524608000
    },
    {
      "id": 207,
      "scenario_id": 4,
      "disp_order": 2050,
      "group_id": 2050,
      "rank": 2,
      "chara_data_id": 0,
      "user_show": 1,
      "receive_condition_type": 3,
      "start_date": 1773352800,
      "end_date": 2524608000
    },
    {
      "id": 208,
      "scenario_id": 4,
      "disp_order": 2051,
      "group_id": 2051,
      "rank": 2,
      "chara_data_id": 0,
      "user_show": 1,
      "receive_condition_type": 3,
      "start_date": 1773352800,
      "end_date": 2524608000
    },
    {
      "id": 209,
      "scenario_id": 4,
      "disp_order": 2052,
      "group_id": 2052,
      "rank": 2,
      "chara_data_id": 0,
      "user_show": 1,
      "receive_condition_type": 3,
      "start_date": 1773352800,
      "end_date": 2524608000
    },
    {
      "id": 210,
      "scenario_id": 4,
      "disp_order": 2053,
      "group_id": 2053,
      "rank": 2,
      "chara_data_id": 0,
      "user_show": 1,
      "receive_condition_type": 3,
      "start_date": 1773352800,
      "end_date": 2524608000
    },
    {
      "id": 211,
      "scenario_id": 4,
      "disp_order": 2054,
      "group_id": 2054,
      "rank": 2,
      "chara_data_id": 0,
      "user_show": 1,
      "receive_condition_type": 3,
      "start_date": 1773352800,
      "end_date": 2524608000
    },
    {
      "id": 212,
      "scenario_id": 4,
      "disp_order": 2055,
      "group_id": 2055,
      "rank": 2,
      "chara_data_id": 0,
      "user_show": 1,
      "receive_condition_type": 3,
      "start_date": 1773352800,
      "end_date": 2524608000
    },
    {
      "id": 213,
      "scenario_id": 4,
      "disp_order": 2056,
      "group_id": 2056,
      "rank": 2,
      "chara_data_id": 0,
      "user_show": 1,
      "receive_condition_type": 3,
      "start_date": 1773352800,
      "end_date": 2524608000
    },
    {
      "id": 214,
      "scenario_id": 4,
      "disp_order": 2057,
      "group_id": 2057,
      "rank": 2,
      "chara_data_id": 0,
      "user_show": 1,
      "receive_condition_type": 3,
      "start_date": 1773352800,
      "end_date": 2524608000
    },
    {
      "id": 215,
      "scenario_id": 4,
      "disp_order": 2058,
      "group_id": 2058,
      "rank": 2,
      "chara_data_id": 0,
      "user_show": 1,
      "receive_condition_type": 3,
      "start_date": 1773352800,
      "end_date": 2524608000
    },
    {
      "id": 216,
      "scenario_id": 4,
      "disp_order": 2059,
      "group_id": 2059,
      "rank": 2,
      "chara_data_id": 0,
      "user_show": 1,
      "receive_condition_type": 3,
      "start_date": 1773352800,
      "end_date": 2524608000
    },
    {
      "id": 217,
      "scenario_id": 4,
      "disp_order": 47,
      "group_id": 47,
      "rank": 1,
      "chara_data_id": 0,
      "user_show": 1,
      "receive_condition_type": 3,
      "start_date": 1773352800,
      "end_date": 2524608000
    },
    {
      "id": 218,
      "scenario_id": 4,
      "disp_order": 48,
      "group_id": 48,
      "rank": 1,
      "chara_data_id": 0,
      "user_show": 1,
      "receive_condition_type": 3,
      "start_date": 1773352800,
      "end_date": 2524608000
    },
    {
      "id": 219,
      "scenario_id": 4,
      "disp_order": 49,
      "group_id": 49,
      "rank": 1,
      "chara_data_id": 0,
      "user_show": 1,
      "receive_condition_type": 3,
      "start_date": 1773352800,
      "end_date": 2524608000
    },
    {
      "id": 220,
      "scenario_id": 4,
      "disp_order": 50,
      "group_id": 50,
      "rank": 1,
      "chara_data_id": 0,
      "user_show": 1,
      "receive_condition_type": 3,
      "start_date": 1773352800,
      "end_date": 2524608000
    },
    {
      "id": 221,
      "scenario_id": 4,
      "disp_order": 51,
      "group_id": 51,
      "rank": 1,
      "chara_data_id": 0,
      "user_show": 1,
      "receive_condition_type": 3,
      "start_date": 1773352800,
      "end_date": 2524608000
    },
    {
      "id": 222,
      "scenario_id": 4,
      "disp_order": 52,
      "group_id": 52,
      "rank": 1,
      "chara_data_id": 0,
      "user_show": 1,
      "receive_condition_type": 3,
      "start_date": 1773352800,
      "end_date": 2524608000
    }
  ]
}